{
  "file": "hex-beast-of-ill-omen-su.md",
  "source_path": "https://www.d20pfsrd.com/classes/base-classes/witch/hexes/hexes/common-hexes/hex-beast-of-ill-omen-su/",
  "source_name": "Witch Hex: Beast of Ill-Omen (Su)",
  "sections": [
    {
      "id": "hex_beast_of_ill_omen_su",
      "title": "Beast of Ill-Omen",
      "anchor_heading": "# Beast of Ill-Omen (Su)",
      "description": "Rules and description for Beast of Ill-Omen.",
      "keywords": []
    }
  ],
  "category": "Witch Hexes"
}