{
  "file": "teisatsu-vigilante-archetype.md",
  "source_path": "https://www.d20pfsrd.com/classes/base-classes/vigilante/archetypes/vigilante-archetypes-paizo-inc/teisatsu-vigilante-archetype/",
  "source_name": "Archetype: Teisatsu",
  "sections": [
    {
      "id": "teisatsu_vigilante_archetype",
      "title": "Teisatsu",
      "anchor_heading": "# Teisatsu",
      "description": "Complete description of the Teisatsu archetype, including altered or replaced class features.",
      "keywords": []
    }
  ],
  "category": "Archetypes"
}