{
  "file": "infernal-blood-greater-su.md",
  "source_path": "https://www.d20pfsrd.com/classes/core-classes/barbarian/rage-powers/paizo-rage-powers/infernal-blood-greater-su/",
  "source_name": "Rage Power: Infernal Blood, Greater (Su)",
  "sections": [
    {
      "id": "infernal_blood_greater_su",
      "title": "Infernal Blood, Greater",
      "anchor_heading": "# Infernal Blood, Greater (Su)",
      "description": "Rules and description for Infernal Blood, Greater.",
      "keywords": []
    }
  ],
  "category": "Rage Powers"
}