{
  "file": "salamander-bloodrager-bloodline.md",
  "source_path": "https://www.d20pfsrd.com/classes/hybrid-classes/bloodrager/bloodrager-bloodlines/paizo-bloodrager-bloodlines/salamander-bloodrager-bloodline/",
  "source_name": "Bloodrager Bloodline: Salamander",
  "sections": [
    {
      "id": "salamander_bloodrager_bloodline",
      "title": "Salamander",
      "anchor_heading": "# Salamander",
      "description": "Rules and description for Salamander.",
      "keywords": []
    }
  ],
  "category": "Bloodrager Bloodlines"
}