{
  "file": "air-totem-greater-su.md",
  "source_path": "https://www.d20pfsrd.com/classes/core-classes/barbarian/rage-powers/paizo-rage-powers/air-totem-greater-su/",
  "source_name": "Rage Power: Elemental Totem, Greater \u2013 Air (Su)",
  "sections": [
    {
      "id": "air_totem_greater_su",
      "title": "Elemental Totem, Greater \u2013 Air",
      "anchor_heading": "# Elemental Totem, Greater \u2013 Air (Su)",
      "description": "Rules and description for Elemental Totem, Greater \u2013 Air.",
      "keywords": []
    }
  ],
  "category": "Rage Powers"
}