{
  "file": "lantern-lighter-ranger-archetype.md",
  "source_path": "https://www.d20pfsrd.com/classes/core-classes/ranger/archetypes/paizo-ranger-archetypes/lantern-lighter-ranger-archetype/",
  "source_name": "Archetype: Lantern Lighter",
  "sections": [
    {
      "id": "lantern_lighter_ranger_archetype",
      "title": "Lantern Lighter",
      "anchor_heading": "# Lantern Lighter",
      "description": "Complete description of the Lantern Lighter archetype, including altered or replaced class features.",
      "keywords": []
    }
  ],
  "category": "Archetypes"
}