{
  "file": "improved-cleaving-finish-combat.md",
  "source_path": "https://www.d20pfsrd.com/feats/combat-feats/improved-cleaving-finish-combat/",
  "source_name": "Feat: Improved Cleaving Finish (Combat)",
  "sections": [
    {
      "id": "improved_cleaving_finish_combat",
      "title": "Improved Cleaving Finish",
      "anchor_heading": "# Improved Cleaving Finish (Combat)",
      "description": "Complete rules for the feat Improved Cleaving Finish, including prerequisites and benefits.",
      "keywords": []
    }
  ],
  "category": "Feats"
}