{
  "file": "haunted-gnome-shroud-combat.md",
  "source_path": "https://www.d20pfsrd.com/feats/combat-feats/haunted-gnome-shroud-combat/",
  "source_name": "Feat: Haunted Gnome Shroud (Combat)",
  "sections": [
    {
      "id": "haunted_gnome_shroud_combat",
      "title": "Haunted Gnome Shroud",
      "anchor_heading": "# Haunted Gnome Shroud (Combat)",
      "description": "Complete rules for the feat Haunted Gnome Shroud, including prerequisites and benefits.",
      "keywords": []
    }
  ],
  "category": "Feats"
}