{
  "file": "master-siege-engineer-combat.md",
  "source_path": "https://www.d20pfsrd.com/feats/combat-feats/master-siege-engineer-combat/",
  "source_name": "Feat: Master Siege Engineer (Combat)",
  "sections": [
    {
      "id": "master_siege_engineer_combat",
      "title": "Master Siege Engineer",
      "anchor_heading": "# Master Siege Engineer (Combat)",
      "description": "Complete rules for the feat Master Siege Engineer, including prerequisites and benefits.",
      "keywords": []
    }
  ],
  "category": "Feats"
}