{
  "file": "upsetting-vengeance-combat.md",
  "source_path": "https://www.d20pfsrd.com/feats/combat-feats/upsetting-vengeance-combat/",
  "source_name": "Feat: Upsetting Vengeance (Combat)",
  "sections": [
    {
      "id": "upsetting_vengeance_combat",
      "title": "Upsetting Vengeance",
      "anchor_heading": "# Upsetting Vengeance (Combat)",
      "description": "Complete rules for the feat Upsetting Vengeance, including prerequisites and benefits.",
      "keywords": []
    }
  ],
  "category": "Feats"
}