{
  "file": "reflexive-crystalline-dust.md",
  "source_path": "https://www.d20pfsrd.com/feats/general-feats/reflexive-crystalline-dust/",
  "source_name": "Feat: Reflexive Crystalline Dust",
  "sections": [
    {
      "id": "reflexive_crystalline_dust",
      "title": "Reflexive Crystalline Dust",
      "anchor_heading": "# Reflexive Crystalline Dust",
      "description": "Complete rules for the feat Reflexive Crystalline Dust, including prerequisites and benefits.",
      "keywords": []
    }
  ],
  "category": "Feats"
}