{
  "file": "hero-s-defiance.md",
  "source_path": "https://www.d20pfsrd.com/magic/all-spells/h/hero-s-defiance/",
  "source_name": "Spell: Hero\u2019s Defiance",
  "sections": [
    {
      "id": "hero_s_defiance",
      "title": "Hero\u2019s Defiance",
      "anchor_heading": "# Hero\u2019s Defiance",
      "includes_subheadings": [],
      "description": "Full description of the spell Hero\u2019s Defiance, including casting time, components, range, and effects.",
      "keywords": []
    }
  ],
  "category": "Spells"
}