{
  "file": "blessing-of-the-salamander.md",
  "source_path": "https://www.d20pfsrd.com/magic/all-spells/b/blessing-of-the-salamander/",
  "source_name": "Spell: Blessing of the Salamander",
  "sections": [
    {
      "id": "blessing_of_the_salamander",
      "title": "Blessing of the Salamander",
      "anchor_heading": "# Blessing of the Salamander",
      "includes_subheadings": [],
      "description": "Full description of the spell Blessing of the Salamander, including casting time, components, range, and effects.",
      "keywords": []
    }
  ],
  "category": "Spells"
}