{
  "file": "nogitsune.md",
  "source_path": "https://www.d20pfsrd.com/classes/core-classes/sorcerer/archetypes/paizo-sorcerer-archetypes/wildblooded/mutated-bloodlines-everyman-gaming-llc/nogitsune/",
  "source_name": "Archetype: Nogitsune Bloodline",
  "sections": [
    {
      "id": "nogitsune",
      "title": "Nogitsune Bloodline",
      "anchor_heading": "# Nogitsune Bloodline",
      "description": "Complete description of the Nogitsune Bloodline archetype, including altered or replaced class features.",
      "keywords": []
    }
  ],
  "category": "Archetypes"
}