{
  "file": "greater-inspiring-cognatogen-su.md",
  "source_path": "https://www.d20pfsrd.com/classes/base-classes/alchemist/discoveries/paizo-alchemist-discoveries/greater-inspiring-cognatogen-su/",
  "source_name": "Alchemist Discovery: Greater Inspiring Cognatogen (Su)",
  "sections": [
    {
      "id": "greater_inspiring_cognatogen_su",
      "title": "Greater Inspiring Cognatogen",
      "anchor_heading": "# Greater Inspiring Cognatogen (Su)",
      "description": "Rules and description for Greater Inspiring Cognatogen.",
      "keywords": []
    }
  ],
  "category": "Alchemist Discoveries"
}