{
  "file": "heister-rogue-archetype.md",
  "source_path": "https://www.d20pfsrd.com/classes/core-classes/rogue/archetypes/paizo-rogue-archetypes/heister-rogue-archetype/",
  "source_name": "Archetype: Heister",
  "sections": [
    {
      "id": "heister_rogue_archetype",
      "title": "Heister",
      "anchor_heading": "# Heister",
      "description": "Complete description of the Heister archetype, including altered or replaced class features.",
      "keywords": []
    }
  ],
  "category": "Archetypes"
}