{
  "file": "instigator-skald-archetype.md",
  "source_path": "https://www.d20pfsrd.com/classes/hybrid-classes/skald/archetypes/paizo-skald-archetypes/instigator-skald-archetype/",
  "source_name": "Archetype: Instigator",
  "sections": [
    {
      "id": "instigator_skald_archetype",
      "title": "Instigator",
      "anchor_heading": "# Instigator",
      "description": "Complete description of the Instigator archetype, including altered or replaced class features.",
      "keywords": []
    }
  ],
  "category": "Archetypes"
}