{
  "file": "stock-striker-style-combat-style.md",
  "source_path": "https://www.d20pfsrd.com/feats/combat-feats/stock-striker-style-combat-style/",
  "source_name": "Feat: Stock-Striker Style (Combat, Style)",
  "sections": [
    {
      "id": "stock_striker_style_combat_style",
      "title": "Stock-Striker Style",
      "anchor_heading": "# Stock-Striker Style (Combat, Style)",
      "description": "Complete rules for the feat Stock-Striker Style, including prerequisites and benefits.",
      "keywords": []
    }
  ],
  "category": "Feats"
}