{
  "file": "arcane-armor-training-combat.md",
  "source_path": "https://www.d20pfsrd.com/feats/combat-feats/arcane-armor-training-combat/",
  "source_name": "Feat: Arcane Armor Training (Combat)",
  "sections": [
    {
      "id": "arcane_armor_training_combat",
      "title": "Arcane Armor Training",
      "anchor_heading": "# Arcane Armor Training (Combat)",
      "description": "Complete rules for the feat Arcane Armor Training, including prerequisites and benefits.",
      "keywords": []
    }
  ],
  "category": "Feats"
}