{
  "file": "reward-of-the-faithful.md",
  "source_path": "https://www.d20pfsrd.com/feats/general-feats/reward-of-the-faithful/",
  "source_name": "Feat: Reward of the Faithful",
  "sections": [
    {
      "id": "reward_of_the_faithful",
      "title": "Reward of the Faithful",
      "anchor_heading": "# Reward of the Faithful",
      "description": "Complete rules for the feat Reward of the Faithful, including prerequisites and benefits.",
      "keywords": []
    }
  ],
  "category": "Feats"
}