{
  "file": "scarring-spell-like-ability-monster.md",
  "source_path": "https://www.d20pfsrd.com/feats/monster-feats/scarring-spell-like-ability-monster/",
  "source_name": "Feat: Scarring Spell-Like Ability (Monster)",
  "sections": [
    {
      "id": "scarring_spell_like_ability_monster",
      "title": "Scarring Spell-Like Ability",
      "anchor_heading": "# Scarring Spell-Like Ability (Monster)",
      "description": "Complete rules for the feat Scarring Spell-Like Ability, including prerequisites and benefits.",
      "keywords": []
    }
  ],
  "category": "Feats"
}