{
  "file": "shield-companion-1.md",
  "source_path": "https://www.d20pfsrd.com/magic/all-spells/s/shield-companion-1/",
  "source_name": "Spell: Shield Companion (ACG)",
  "sections": [
    {
      "id": "shield_companion_1",
      "title": "Shield Companion (ACG)",
      "anchor_heading": "# Shield Companion (ACG)",
      "description": "Full description of the spell Shield Companion (ACG), including casting time, components, range, and effects.",
      "keywords": []
    }
  ],
  "category": "Spells"
}