{
  "file": "perception.md",
  "source_path": "https://www.d20pfsrd.com/skills/perception/",
  "source_name": "Skill: Perception (Wis)",
  "sections": [
    {
      "id": "perception",
      "title": "Perception (Wis)",
      "anchor_heading": "# Perception (Wis)",
      "includes_subheadings": [
        "### Common Uses",
        "#### Notice Someone/Something",
        "### Action",
        "### Modifiers",
        "#### Perception Unchained",
        "### FYI\u2026",
        "### Get Organized!",
        "### Unofficial Extras!"
      ],
      "description": "Rules for the Perception skill, including DCs for noticing creatures and objects, environmental modifiers, opposed checks against Stealth, and skill unlock abilities at higher ranks.",
      "keywords": [
        "Perception",
        "Notice",
        "Stealth check",
        "opposed check",
        "secret door",
        "concealed door",
        "pickpocket",
        "invisible creature",
        "trap detection",
        "skill unlock",
        "Perception Unchained",
        "distance modifier",
        "sleeping",
        "lip reading",
        "trap spotter"
      ]
    }
  ],
  "category": "Skills"
}